{
  "updated": "2026-07-13T22:07:54.821336+00:00",
  "rankings": [
    {
      "ticker": "RKLB",
      "score": 93,
      "score_addon": 36,
      "price": 76.73,
      "upside_pct": 51.8,
      "rsi": 35.0,
      "divergence": "pass",
      "trigger": "warn",
      "signal": {
        "signal": "none",
        "reasons": []
      },
      "signal_addon": {
        "signal": "none",
        "reasons": []
      },
      "uptrend_entry_signal": null,
      "divergence_invalidated_signal": null,
      "divergence_stop_signal": null
    },
    {
      "ticker": "IREN",
      "score": 57,
      "score_addon": 21,
      "price": 38.98,
      "upside_pct": 107.6,
      "rsi": 36.3,
      "divergence": "warn",
      "trigger": "fail",
      "signal": {
        "signal": "none",
        "reasons": []
      },
      "signal_addon": {
        "signal": "none",
        "reasons": []
      },
      "uptrend_entry_signal": null,
      "divergence_invalidated_signal": null,
      "divergence_stop_signal": null
    },
    {
      "ticker": "PEP",
      "score": 53,
      "score_addon": 42,
      "price": 138.49,
      "upside_pct": 12.9,
      "rsi": 43.2,
      "divergence": "warn",
      "trigger": "pass",
      "signal": {
        "signal": "none",
        "reasons": []
      },
      "signal_addon": {
        "signal": "none",
        "reasons": []
      },
      "uptrend_entry_signal": null,
      "divergence_invalidated_signal": null,
      "divergence_stop_signal": null
    },
    {
      "ticker": "AVEX",
      "score": 47,
      "score_addon": 36,
      "price": 15.91,
      "upside_pct": 124.7,
      "rsi": 37.5,
      "divergence": "warn",
      "trigger": "warn",
      "signal": {
        "signal": "none",
        "reasons": []
      },
      "signal_addon": {
        "signal": "none",
        "reasons": []
      },
      "uptrend_entry_signal": null,
      "divergence_invalidated_signal": null,
      "divergence_stop_signal": null
    },
    {
      "ticker": "LMT",
      "score": 40,
      "score_addon": 57,
      "price": 520.68,
      "upside_pct": 18.3,
      "rsi": 49.1,
      "divergence": "warn",
      "trigger": "fail",
      "signal": {
        "signal": "none",
        "reasons": []
      },
      "signal_addon": {
        "signal": "down",
        "reasons": [
          {
            "label": "구간 하향 이탈",
            "detail": null
          },
          {
            "label": "3일 연속 하락",
            "detail": null
          }
        ]
      },
      "uptrend_entry_signal": null,
      "divergence_invalidated_signal": null,
      "divergence_stop_signal": null
    },
    {
      "ticker": "TTWO",
      "score": 40,
      "score_addon": 57,
      "price": 244.1,
      "upside_pct": 16.4,
      "rsi": 55.6,
      "divergence": "warn",
      "trigger": "fail",
      "signal": {
        "signal": "none",
        "reasons": []
      },
      "signal_addon": {
        "signal": "down",
        "reasons": [
          {
            "label": "구간 하향 이탈",
            "detail": null
          }
        ]
      },
      "uptrend_entry_signal": null,
      "divergence_invalidated_signal": null,
      "divergence_stop_signal": null
    },
    {
      "ticker": "VOYG",
      "score": 40,
      "score_addon": 21,
      "price": 29.66,
      "upside_pct": 46.5,
      "rsi": 39.3,
      "divergence": "warn",
      "trigger": "fail",
      "signal": {
        "signal": "none",
        "reasons": []
      },
      "signal_addon": {
        "signal": "none",
        "reasons": []
      },
      "uptrend_entry_signal": null,
      "divergence_invalidated_signal": null,
      "divergence_stop_signal": null
    },
    {
      "ticker": "TOYO",
      "score": 30,
      "score_addon": 21,
      "price": 5.75,
      "upside_pct": 187.0,
      "rsi": 26.5,
      "divergence": "fail",
      "trigger": "fail",
      "signal": {
        "signal": "none",
        "reasons": []
      },
      "signal_addon": {
        "signal": "none",
        "reasons": []
      },
      "uptrend_entry_signal": null,
      "divergence_invalidated_signal": {
        "active": true,
        "prior_divergence_date_index": 248,
        "days_since_prior_divergence": 2,
        "price_drop_since_pct": 6.8
      },
      "divergence_stop_signal": null
    },
    {
      "ticker": "STZ",
      "score": 30,
      "score_addon": 36,
      "price": 134.51,
      "upside_pct": 27.1,
      "rsi": 42.0,
      "divergence": "fail",
      "trigger": "pass",
      "signal": {
        "signal": "none",
        "reasons": []
      },
      "signal_addon": {
        "signal": "none",
        "reasons": []
      },
      "uptrend_entry_signal": {
        "active": true,
        "days_since_divergence": 3,
        "gain_since_low_pct": 3.2,
        "divergence_date_index": 247
      },
      "divergence_invalidated_signal": null,
      "divergence_stop_signal": null
    },
    {
      "ticker": "AMSC",
      "score": 30,
      "score_addon": 36,
      "price": 34.18,
      "upside_pct": 91.1,
      "rsi": 34.9,
      "divergence": "fail",
      "trigger": "pass",
      "signal": {
        "signal": "none",
        "reasons": []
      },
      "signal_addon": {
        "signal": "none",
        "reasons": []
      },
      "uptrend_entry_signal": null,
      "divergence_invalidated_signal": {
        "active": true,
        "prior_divergence_date_index": 246,
        "days_since_prior_divergence": 4,
        "price_drop_since_pct": 3.9
      },
      "divergence_stop_signal": null
    },
    {
      "ticker": "NXT",
      "score": 30,
      "score_addon": 36,
      "price": 99.67,
      "upside_pct": 51.3,
      "rsi": 35.9,
      "divergence": "fail",
      "trigger": "warn",
      "signal": {
        "signal": "none",
        "reasons": []
      },
      "signal_addon": {
        "signal": "none",
        "reasons": []
      },
      "uptrend_entry_signal": null,
      "divergence_invalidated_signal": null,
      "divergence_stop_signal": null
    },
    {
      "ticker": "INFQ",
      "score": 30,
      "score_addon": 36,
      "price": 10.13,
      "upside_pct": 107.3,
      "rsi": 35.2,
      "divergence": "fail",
      "trigger": "warn",
      "signal": {
        "signal": "none",
        "reasons": []
      },
      "signal_addon": {
        "signal": "none",
        "reasons": []
      },
      "uptrend_entry_signal": null,
      "divergence_invalidated_signal": null,
      "divergence_stop_signal": null
    },
    {
      "ticker": "FSLR",
      "score": 30,
      "score_addon": 36,
      "price": 221.03,
      "upside_pct": 14.0,
      "rsi": 37.4,
      "divergence": "fail",
      "trigger": "pass",
      "signal": {
        "signal": "none",
        "reasons": []
      },
      "signal_addon": {
        "signal": "none",
        "reasons": []
      },
      "uptrend_entry_signal": null,
      "divergence_invalidated_signal": {
        "active": true,
        "prior_divergence_date_index": 247,
        "days_since_prior_divergence": 3,
        "price_drop_since_pct": 1.5
      },
      "divergence_stop_signal": null
    },
    {
      "ticker": "PFE",
      "score": 27,
      "score_addon": 21,
      "price": 24.48,
      "upside_pct": 18.2,
      "rsi": 46.3,
      "divergence": "fail",
      "trigger": "fail",
      "signal": {
        "signal": "none",
        "reasons": []
      },
      "signal_addon": {
        "signal": "down",
        "reasons": [
          {
            "label": "급락 기준 (-25 이상)",
            "detail": "전일 57 → 오늘 21 (전일 대비 -36)"
          },
          {
            "label": "구간 하향 이탈",
            "detail": null
          }
        ]
      },
      "uptrend_entry_signal": null,
      "divergence_invalidated_signal": null,
      "divergence_stop_signal": null
    },
    {
      "ticker": "SMCI",
      "score": 27,
      "score_addon": 21,
      "price": 27.66,
      "upside_pct": 34.7,
      "rsi": 41.9,
      "divergence": "fail",
      "trigger": "fail",
      "signal": {
        "signal": "none",
        "reasons": []
      },
      "signal_addon": {
        "signal": "none",
        "reasons": []
      },
      "uptrend_entry_signal": null,
      "divergence_invalidated_signal": {
        "active": true,
        "prior_divergence_date_index": 245,
        "days_since_prior_divergence": 1,
        "price_drop_since_pct": 3.5
      },
      "divergence_stop_signal": null
    },
    {
      "ticker": "LASR",
      "score": 27,
      "score_addon": 61,
      "price": 68.79,
      "upside_pct": 31.9,
      "rsi": 51.6,
      "divergence": "fail",
      "trigger": "fail",
      "signal": {
        "signal": "none",
        "reasons": []
      },
      "signal_addon": {
        "signal": "none",
        "reasons": []
      },
      "uptrend_entry_signal": {
        "active": true,
        "days_since_divergence": 3,
        "gain_since_low_pct": 17.2,
        "divergence_date_index": 247
      },
      "divergence_invalidated_signal": null,
      "divergence_stop_signal": null
    },
    {
      "ticker": "SIF",
      "score": 20,
      "score_addon": 61,
      "price": 22.3,
      "upside_pct": null,
      "rsi": 52.2,
      "divergence": "fail",
      "trigger": "warn",
      "signal": {
        "signal": "none",
        "reasons": []
      },
      "signal_addon": {
        "signal": "down",
        "reasons": [
          {
            "label": "구간 하향 이탈",
            "detail": null
          }
        ]
      },
      "uptrend_entry_signal": null,
      "divergence_invalidated_signal": null,
      "divergence_stop_signal": null
    }
  ]
}