{
  "ticker": "RKLB",
  "price": 81.04,
  "updated": "2026-07-13T10:58:37.300901+00:00",
  "as_of_date": "2026-07-10",
  "score": 60,
  "stages": {
    "1_market_health": {
      "status": "neutral",
      "index_name": "나스닥",
      "index_symbol": "^IXIC",
      "etf": "QQQ",
      "volume_diff_pct_3m": -39.9,
      "price_up_latest": true
    },
    "2_fundamentals": {
      "status": "pass",
      "upside_pct": 43.8,
      "forward_pe": 2701.3335,
      "peg": null
    },
    "3_divergence_gate": {
      "status": "warn",
      "bullish_divergence": false,
      "divergence_present": true,
      "gap_days": 10,
      "signal_fresh": true
    },
    "4_zscore": {
      "status": "warn",
      "rsi": 37.3,
      "rsi_zscore_1y": -1.39
    },
    "5_trigger_candle": {
      "status": "warn",
      "breakout_confirmed": false,
      "pattern": null,
      "days_ago": null,
      "hammer": false,
      "bullish_engulfing": false,
      "morning_star": false,
      "long_lower_wick": true,
      "wick_days_ago": 0,
      "adx_reference": 24.0
    }
  },
  "entry_atr_stop_pct": 16.2,
  "score_addon": 35,
  "stages_addon": {
    "1_fundamentals": {
      "status": "pass",
      "upside_pct": 43.8,
      "forward_pe": 2701.3335,
      "peg": null
    },
    "2_pullback_gate": {
      "status": "fail",
      "near_sma20": false,
      "near_sma40": false,
      "ma_converged_ignored": false
    },
    "3_rsi_zone": {
      "status": "fail",
      "rsi": 37.3
    },
    "4_trigger_confirmed": {
      "status": "fail",
      "setup_confirmed": false,
      "setup_days_ago": null,
      "trigger_confirmed": false,
      "trigger_lag": null
    },
    "9_position_sizing": {
      "stop_pct_from_20sma": 18.2
    }
  },
  "sector": "Industrials",
  "sector_relative_strength_up": true,
  "uptrend_entry_signal": null,
  "divergence_invalidated_signal": null,
  "pullback_stop_signal": {
    "stop_reference_price": 81.04,
    "stopped_out": false
  },
  "divergence_stop_signal": null
}